pipen_runinfo/__init__.py
pipen_runinfo/session_info.py
pipen_runinfo/version.py
pipen_runinfo-1.1.2.dist-info/METADATA
pipen_runinfo-1.1.2.dist-info/WHEEL
pipen_runinfo-1.1.2.dist-info/entry_points.txt
pipen_runinfo-1.1.2.dist-info/RECORD
